cvdnet_pipeline/analyse_giessen.py
cvdnet_pipeline/build_emulator.py
cvdnet_pipeline/calibrate_parameters.py
cvdnet_pipeline/compute_pca.py
cvdnet_pipeline/kalman_filter_giessen.py
cvdnet_pipeline/run_pipeline.py
cvdnet_pipeline/sensitivity_analysis.py
cvdnet_pipeline/simulate_data.py
cvdnet_pipeline/utils/bayesian_calibration.py
cvdnet_pipeline/utils/constants.py
cvdnet_pipeline/utils/helper_functions.py
cvdnet_pipeline/utils/kf_emulator.py
cvdnet_pipeline/utils/plot_utils.py
cvdnet_pipeline-0.1.0.dist-info/METADATA
cvdnet_pipeline-0.1.0.dist-info/WHEEL
cvdnet_pipeline-0.1.0.dist-info/entry_points.txt
cvdnet_pipeline-0.1.0.dist-info/top_level.txt
cvdnet_pipeline-0.1.0.dist-info/RECORD
