Metadata-Version: 2.4
Name: cvdnet-pipeline
Version: 0.1.0
Summary: A pipeline for performing rapid calibration of 0D cardiovascular models using linear emulators.
Author-email: Fay Frost <fay.frost@nottingham.ac.uk>, Levan Bokeria <levan.bokeria@gmail.com>
License-Expression: MIT
Project-URL: Homepage, https://github.com/alan-turing-institute/cvd-net-pipeline
Project-URL: Source Code, https://github.com/alan-turing-institute/cvd-net-pipeline
Project-URL: Bug Tracker, https://github.com/alan-turing-institute/cvd-net-pipeline/issues
Requires-Python: >=3.12
Requires-Dist: pandas
Requires-Dist: numpy
Requires-Dist: ModularCirc
Requires-Dist: pytest
Requires-Dist: giessen-data-analysis
Requires-Dist: seaborn
Requires-Dist: salib
Provides-Extra: notebooks
Requires-Dist: ipykernel; extra == "notebooks"
Provides-Extra: dev
Requires-Dist: pre-commit; extra == "dev"
Requires-Dist: black; extra == "dev"
Requires-Dist: flake8; extra == "dev"
Requires-Dist: isort; extra == "dev"
